<pocketitems>
	<card type="suit" pickup="2" description="Item multiplier" hud="Two of Shields" name="Two of Shields" mimiccharge="12" />
	<card type="suit" pickup="2" description="Convert all" hud="Ace of Shields" name="Ace of Shields" mimiccharge="12" />
	<card type="special" pickup="8" description="It's time to duel" hud="Trap Card" name="Trap Card" mimiccharge="1" />
	<card type="special" pickup="8" description="High level access" hud="Key Card" name="Key Card" mimiccharge="6" />
	<card type="special" pickup="99" description="???" hud="Golden Card" name="Golden Card" mimiccharge="12" />
	<card type="rune" pickup="104" description="Heartache" hud="Soul of Leah" name="Soul of Leah" achievement="Soul of Leah" mimiccharge="6" />
	<card type="rune" pickup="105" description="Your world, born again" hud="Soul of Peter" name="Soul of Peter" achievement="Soul of Peter" mimiccharge="6" />
	<card type="rune" pickup="106" description="Drown" hud="Soul of Miriam" name="Soul of Miriam" achievement="Soul of Miriam" mimiccharge="12" />
	<card type="rune" pickup="111" description="Deep affection" hud="Essence of Love" name="Essence of Love" achievement="Essence of Love" mimiccharge="3" />
	<card type="rune" pickup="112" description="Regret" hud="Essence of Hate" name="Essence of Hate" achievement="Essence of Hate" mimiccharge="6" />
	<card type="rune" pickup="113" description="Between birth and death" hud="Essence of Life" name="Essence of Life" achievement="Essence of Life" mimiccharge="2" />
	<card type="rune" pickup="114" description="Permanence" hud="Essence of Death" name="Essence of Death" achievement="Essence of Death" mimiccharge="4" />
	<card type="rune" pickup="115" description="Buoyant" hud="Essence of Deluge" name="Essence of Deluge" achievement="Essence of Deluge" mimiccharge="1" />
	<card type="rune" pickup="116" description="Shortage" hud="Essence of Drought" name="Essence of Drought" name="Essence of Drought" mimiccharge="2" />
	<card type="tarot" pickup="1" description="May your future be bright and successful" hud="Hope" name="XXIII - Hope" mimiccharge="2" />
	<card type="tarot_reverse" pickup="14" description="I have a bad feeling about this" hud="ReverseHope" name="XXIII - Hope?" achievement="Reverse Hope" mimiccharge="2" />
	<card type="tarot" pickup="1" description="May your soul find salvation" hud="Faith" name="XXV - Faith" mimiccharge="2" />
	<card type="tarot_reverse" pickup="14" description="Give up your spirit" hud="ReverseFaith" name="XXV - Faith?" achievement="Reverse Faith" mimiccharge="2" />
	<card type="tarot" pickup="1" description="To each according to his needs" hud="Charity" name="XXIV - Charity" mimiccharge="2" />
	<card type="tarot_reverse" pickup="14" description="Everything comes at a price" hud="ReverseCharity" name="XXIV - Charity?" achievement="Reverse Charity" mimiccharge="2" />

	<card type="object" pickup="119" description="Packaged ghost barrage" hud="Spooky Photo" name="Spooky Photo" achievement="9999" />
	<card type="object" pickup="120" description="Packaged ghost barrage" hud="Haunted Photo" name="Haunted Photo" achievement="9999" />
	<card type="object" pickup="121" description="Packaged ghost barrage" hud="Possessed Photo" name="Possessed Photo" achievement="9999" />
	<card type="object" pickup="122" description="Smells like mod compatibility" hud="Capsule D9" name="Capsule D9" achievement="9999" />
	<card type="object" pickup="123" description="Smells like mod compatibility" hud="Capsule D16" name="Capsule D16" achievement="9999" />

	<pilleffect name="Heartache Up" class="3-" mimiccharge="4" />
	<pilleffect name="Heartache Down" class="3+" mimiccharge="6" />
</pocketitems>